LICENSE
gazetimation.py
gazetimation-0.2.3.dist-info/entry_points.txt
gazetimation-0.2.3.dist-info/LICENSE
gazetimation-0.2.3.dist-info/WHEEL
gazetimation-0.2.3.dist-info/METADATA
gazetimation-0.2.3.dist-info/RECORD
