Metadata-Version: 2.1
Name: gazetimation
Version: 0.2.3
Summary: Gaze estimation from facial landmarks
Home-page: https://github.com/paul-shuvo/gazetimation
License: MIT
Keywords: gaze,gaze estimation,head pose,eye pose
Author: Shuvo Kumar Paul
Author-email: shuvo.k.paul@gmail.com
Requires-Python: >=3.6,<4.0
Classifier: License :: OSI Approved :: MIT License
Classifier: Programming Language :: Python :: 3
Classifier: Programming Language :: Python :: 3.6
Classifier: Programming Language :: Python :: 3.7
Classifier: Programming Language :: Python :: 3.8
Classifier: Programming Language :: Python :: 3.9
Classifier: Programming Language :: Python :: 3.10
Requires-Dist: mediapipe
Requires-Dist: numpy
Requires-Dist: opencv-python
Project-URL: Repository, https://github.com/paul-shuvo/gazetimation
